{
    "params": [
        {
            "N1": 20,
            "N2": 200,
            "T": 600,
            "varphi": 0.1,
            "nu": 0.04,
            "xi": 0.5,
            "o1": 0.3,
            "o2": 0.3,
            "uu11": -0.015,
            "uu21": 0.015,
            "uu12": -0.015,
            "uu22": 0.03,
            "uu31": -0.01,
            "uu41": 0.035,
            "uu32": -0.01,
            "uu42": 0.05,
            "uu51": -0.01,
            "uu61": 0.02,
            "uu52": -0.005,
            "uu62": 0.0025,
            "uinf": -0.15,
            "usup": 0.15,
            "b_a11": 1.5,
            "b_b11": 3,
            "b_a12": 1.5,
            "b_b12": 3,
            "b_a2": 1.5,
            "b_b2": 3,
            "b_a3": 1.5,
            "b_b3": 3,
            "mi1": 0.1,
            "mi2": 0.2,
            "Gamma": 0.32,
            "chi": -1.39,
            "omega1": 20,
            "omega2": 1,
            "psi1": 0.4,
            "psi2": 1,
            "psi3": 0.26,
            "deltami2": 0.01,
            "w_min": 1,
            "pmin": 0.01,
            "theta": 1,
            "u": 0.8,
            "alfa": 0.16,
            "b": 160,
            "dim_mach": 40,
            "agemax": 19,
            "a": 0.1,
            "credit_multiplier": 0.05,
            "beta_basel": 0,
            "bankmarkdown": 1,
            "centralbankmarkdown": 1,
            "d1": 0.75,
            "d2": 0.75,
            "db": 0.5,
            "repayment_share": 0.15,
            "bonds_share": 1,
            "pareto_a": 0.8,
            "pareto_k": 10,
            "pareto_p": 35,
            "d_cpi_target": 0.005,
            "ustar": 0.05,
            "w1sup": 0.5,
            "w1inf": 0.5,
            "w2sup": 0.9,
            "w2inf": 0.1,
            "k_const": 0.1,
            "aliqw": 0,
            "taylor1": 1.23,
            "taylor2": 0.17,
            "bondsmarkdown": 0,
            "mdw": 0.025,
            "phi2": 10,
            "b1sup": 1,
            "b1inf": 1,
            "b2sup": 1,
            "b2inf": 1,
            "aliq": 0.1,
            "aliqb": 0.1,
            "wu": 0.4,
            "de": 0.99,
            "a1": 0.965,
            "a2": 0.3,
            "a3": 0.1,
            "u_low": 0.0001,
            "f2_entry_min": 0.0005,
            "kappa": 0.76,
            "taylor": 0.74,
            "omicron": 0,
            "I_max": 0.25,
            "persistence": 1,
            "omega3": 0.8,
            "d_f": 0.01,
            "g_ls": 0.9999885,
            "aliqe": 1,
            "tre": 1,
            "passthrough": 1,
            "exp_quota_param": 200,
            "ge_subsidy": 0.75
        }
    ],
    "climparams": [
        {
            "share_RD_en": 0.01,
            "share_de_0": 0.6,
            "payback_en": 10,
            "life_plant": 80,
            "exp_quota": 0.015,
            "o1_en": 0.01,
            "uu1_en": -0.01,
            "uu2_en": 0.005,
            "t_start_climbox": 200,
            "T_pre": 14,
            "intercept_temp": -0.2674,
            "slope_temp": 0.0018,
            "tc1": 140,
            "tc2": 1.0346,
            "ndep": 5,
            "laydep1": 100,
            "laydep2": 300,
            "laydep3": 300,
            "laydep4": 1300,
            "laydep5": 1800,
            "fertil": 0.42,
            "heatstress": -0.01,
            "humtime": 27.8,
            "biotime": 10.6,
            "humfrac": 0.428,
            "eddydif": 4400,
            "ConrefT": 0.003,
            "rev0": 9.7,
            "revC": 3.92,
            "niterclim": 5,
            "forCO2": 5.35,
            "otherforcefac": 1.12,
            "outrad": 1.23,
            "secyr": 31557600,
            "seasurf": 0.708,
            "heatcap": 4230000,
            "freqclim": 4,
            "g_emiss_global": 1.0045,
            "emiss_share": 0.1
        }
    ],
    "climshockparams": [
        {
            "nshocks": 9,
            "a1_0": [
                0.005,
                0.005,
                0.005,
                0.005
            ],
            "b1_0": [
                1000,
                1000,
                1000,
                1000
            ],
            "a2_0": [
                1,
                1,
                1,
                1
            ],
            "b2_0": [
                100,
                100,
                100,
                100
            ],
            "a3_0": [
                0.75,
                0.75,
                0.75,
                0.75
            ],
            "b3_0": [
                150,
                150,
                150,
                150
            ],
            "a4_0": [
                0.75,
                0.75,
                0.75,
                0.75
            ],
            "b4_0": [
                150,
                150,
                150,
                150
            ],
            "a5_0": [
                1,
                1,
                1,
                1
            ],
            "b5_0": [
                100,
                100,
                100,
                100
            ],
            "a6_0": [
                1,
                1,
                1,
                1
            ],
            "b6_0": [
                100,
                100,
                100,
                100
            ],
            "a7_0": [
                1,
                1,
                1,
                1
            ],
            "b7_0": [
                100,
                100,
                100,
                100
            ],
            "a8_0": [
                1,
                1,
                1,
                1
            ],
            "b8_0": [
                100,
                100,
                100,
                100
            ],
            "a9_0": [
                0.75,
                0.75,
                0.75,
                0.75
            ],
            "b9_0": [
                150,
                150,
                150,
                150
            ],
            "shockexponent1_1": [
                0.25,
                0.25,
                0.25,
                0.25
            ],
            "shockexponent1_2": [
                0.25,
                0.25,
                0.25,
                0.25
            ],
            "shockexponent2_1": [
                3,
                3,
                3,
                3
            ],
            "shockexponent2_2": [
                8,
                8,
                8,
                8
            ],
            "shockexponent3_1": [
                3,
                3,
                3,
                3
            ],
            "shockexponent3_2": [
                8,
                8,
                8,
                8
            ],
            "shockexponent4_1": [
                3,
                3,
                3,
                3
            ],
            "shockexponent4_2": [
                8,
                8,
                8,
                8
            ],
            "shockexponent5_1": [
                3,
                3,
                3,
                3
            ],
            "shockexponent5_2": [
                8,
                8,
                8,
                8
            ],
            "shockexponent6_1": [
                3,
                3,
                3,
                3
            ],
            "shockexponent6_2": [
                8,
                8,
                8,
                8
            ],
            "shockexponent7_1": [
                3,
                3,
                3,
                3
            ],
            "shockexponent7_2": [
                8,
                8,
                8,
                8
            ],
            "shockexponent8_1": [
                3,
                3,
                3,
                3
            ],
            "shockexponent8_2": [
                8,
                8,
                8,
                8
            ],
            "shockexponent9_1": [
                3,
                3,
                3,
                3
            ],
            "shockexponent9_2": [
                8,
                8,
                8,
                8
            ]
        }
    ],
    "flags": [
        {
            "flag_shockexperiment": 1,
            "flag_exogenousshocks": 0,
            "flag_cum_emissions": 0,
            "flag_tax_CO2": 4,
            "flag_energyshocks": 0,
            "flag_capshocks": 1,
            "flag_outputshocks": 0,
            "flag_inventshocks": 0,
            "flag_encapshocks": 0,
            "flag_popshocks": 0,
            "flag_demandshocks": 0,
            "flag_RDshocks": 0,
            "flag_prodshocks1": 0,
            "flag_prodshocks2": 0,
            "flag_share_END": 2,
            "flag_energy_exp": 3,
            "flagbailout": 0,
            "flag_entry": 0,
            "flag_nonCO2_force": 1,
            "flag_validation": 0,
            "flag_inventories": 0,
            "flag_scrap_age": 1,
            "flag_uniformshocks": 1,
            "flag_desc": 0
        }
    ],
    "inits": [
        {
            "A0": 1,
            "LS0": 250000,
            "W10": 500,
            "W20": 320,
            "L0": 470,
            "w0": 1,
            "K0": 1280,
            "bankmarkup_init": 0.7,
            "A0_en": 1,
            "A0_ef": 60,
            "K_ge0_perc": 0.2,
            "pf0": 1e-05,
            "mi_en0": 0.05,
            "A_de0": 0.01,
            "EM0": 110,
            "CF_ge0": 0.05,
            "t_CO2_0": 0,
            "t_CO2_en_0": 0.000025,
            "r_base": 0.04,
            "d_Am_init": 0.005,
            "D_h0": 250000,
            "NW_b0": 70000,
            "pm": 0.275,
            "D_e0": 10000
        }
    ],
    "climinits": [
        {
            "Emiss_yearly_0": 12,
            "Cum_emissions_0": 600,
            "T_0_cumemiss": 0.8125,
            "Con00": 10.2373,
            "NPP0": 85.1771,
            "Cat0": 590,
            "Catinit0": 809.9168,
            "Coninit01": 1051,
            "Coninit02": 3126,
            "Coninit03": 3103,
            "Coninit04": 13329,
            "Coninit05": 18429,
            "Honinit01": 338410000,
            "Honinit02": 651750000,
            "Honinit03": 370940000,
            "Honinit04": 226040000,
            "Honinit05": 17190000,
            "Toninit01": 0.8,
            "Toninit02": 0.5136,
            "Toninit03": 0.2923,
            "Toninit04": 0.0411,
            "Toninit05": 0.0023,
            "biominit0": 996.7183,
            "huminit0": 1080.7,
            "Catinit1": 864.6616,
            "Coninit11": 1056,
            "Coninit12": 3136,
            "Coninit13": 3110,
            "Coninit14": 13334,
            "Coninit15": 18429,
            "Honinit11": 459220000,
            "Honinit12": 890260000,
            "Honinit13": 512790000,
            "Honinit14": 320730000,
            "Honinit15": 25180000,
            "Toninit11": 1.0856,
            "Toninit12": 0.7015,
            "Toninit13": 0.4041,
            "Toninit14": 0.0583,
            "Toninit15": 0.0033,
            "biominit1": 1014.7,
            "huminit1": 1095
        }
    ],
    "regions": {
        "NR": 4,
        "K_firm_shares": [
            0.25,
            0.25,
            0.25,
            0.25
        ],
        "C_firm_shares": [
            0.25,
            0.25,
            0.25,
            0.25
        ],
        "energy": {
            "dirty_capacity_shares": [
                0.25,
                0.25,
                0.25,
                0.25
            ],
            "green_capacity_shares": [
                0.25,
                0.25,
                0.25,
                0.25
            ]
        },
        "de_growth_probability": [
            0.25,
            0.25,
            0.25,
            0.25
        ],
        "ge_growth_probability": [
            0.25,
            0.25,
            0.25,
            0.25
        ]
    },
    "shocks_kfirms": [
        0,
        0,
        0,
        0,
        0,
        0,
        0,
        0,
        0,
        0,
        0,
        0,
        0,
        0,
        0,
        0,
        0,
        0,
        0,
        0
    ],
    "shocks_cfirms": [
        0,
        0,
        0,
        0,
        0,
        0,
        0,
        0,
        0,
        0,
        0,
        0,
        0,
        0,
        0,
        0,
        0,
        0,
        0,
        0,
        0,
        0,
        0,
        0,
        0,
        0,
        0,
        0,
        0,
        0,
        0,
        0,
        0,
        0,
        0,
        0,
        0,
        0,
        0,
        0,
        0,
        0,
        0,
        0,
        0,
        0,
        0,
        0,
        0,
        0,
        0,
        0,
        0,
        0,
        0,
        0,
        0,
        0,
        0,
        0,
        0,
        0,
        0,
        0,
        0,
        0,
        0,
        0,
        0,
        0,
        0,
        0,
        0,
        0,
        0,
        0,
        0,
        0,
        0,
        0,
        0,
        0,
        0,
        0,
        0,
        0,
        0,
        0,
        0,
        0,
        0,
        0,
        0,
        0,
        0,
        0,
        0,
        0,
        0,
        0,
        0,
        0,
        0,
        0,
        0,
        0,
        0,
        0,
        0,
        0,
        0,
        0,
        0,
        0,
        0,
        0,
        0,
        0,
        0,
        0,
        0,
        0,
        0,
        0,
        0,
        0,
        0,
        0,
        0,
        0,
        0,
        0,
        0,
        0,
        0,
        0,
        0,
        0,
        0,
        0,
        0,
        0,
        0,
        0,
        0,
        0,
        0,
        0,
        0,
        0,
        0,
        0,
        0,
        0,
        0,
        0,
        0,
        0,
        0,
        0,
        0,
        0,
        0,
        0,
        0,
        0,
        0,
        0,
        0,
        0,
        0,
        0,
        0,
        0,
        0,
        0,
        0,
        0,
        0,
        0,
        0,
        0,
        0,
        0,
        0,
        0,
        0,
        0,
        0,
        0,
        0,
        0,
        0,
        0,
        0,
        0,
        0,
        0,
        0,
        0
    ],
    "shock_scalar": 0.15
}